hooked/__init__.py
hooked/admin.py
hooked/apps.py
hooked/hooked.py
hooked/http.py
hooked/models.py
hooked/receivers.py
hooked/tokens.py
hooked/migrations/0001_initial.py
hooked/migrations/__init__.py
django_hooked-0.2.6.dist-info/LICENSE
django_hooked-0.2.6.dist-info/METADATA
django_hooked-0.2.6.dist-info/WHEEL
django_hooked-0.2.6.dist-info/top_level.txt
django_hooked-0.2.6.dist-info/RECORD
